{
  "skills": [
    {
      "type": "Frontend",
      "list": [
        "HTML5",
        "CSS3",
        "JavaScript (ES6+)",
        "React",
        "React Router",
        "TypeScript",
        "Zustand",
        "Styled Components",
        "Accessibility",
        "Responsive Design"
      ]
    },
    {
      "type": "Backend",
      "list": [
        "Node.js",
        "Express.js",
        "MongoDB",
        "Mongoose",
        "RESTful APIs",
        "Bcrypt"
      ]
    },
    {
      "type": "Toolbox",
      "list": [
        "Git & GitHub",
        "VS Code",
        "Postman",
        "Figma",
        "Miro",
        "Slack",
        "Jira"
      ]
    },
    {
      "type": "More",
      "list": [
        "API Integration",
        "Full-stack development",
        "Agile methodology",
        "Digital transformation",
        "System implementation",
        "UX/UI considerations",
        "Zendesk"
      ]
    }
  ]
}